MANIFEST.in
README.rst
setup.py
docs/HISTORY.rst
docs/LICENSE.GPL
docs/LICENSE.txt
seantis/__init__.py
seantis.translators.egg-info/PKG-INFO
seantis.translators.egg-info/SOURCES.txt
seantis.translators.egg-info/dependency_links.txt
seantis.translators.egg-info/entry_points.txt
seantis.translators.egg-info/namespace_packages.txt
seantis.translators.egg-info/not-zip-safe
seantis.translators.egg-info/requires.txt
seantis.translators.egg-info/top_level.txt
seantis/translators/__init__.py
seantis/translators/configure.zcml
seantis/translators/interfaces.py
seantis/translators/profiles.zcml
seantis/translators/setuphandler.py
seantis/translators/sync.sh
seantis/translators/testing.py
seantis/translators/upgrades.py
seantis/translators/upgrades.zcml
seantis/translators/vocabularies.py
seantis/translators/browser/__init__.py
seantis/translators/browser/base.py
seantis/translators/browser/configure.zcml
seantis/translators/locales/seantis.translators.pot
seantis/translators/locales/de/LC_MESSAGES/seantis.people.po
seantis/translators/locales/de/LC_MESSAGES/seantis.translators.po
seantis/translators/profiles/default/browserlayer.xml
seantis/translators/profiles/default/metadata.xml
seantis/translators/profiles/default/seantis.translators-default.txt
seantis/translators/profiles/default/types.xml
seantis/translators/profiles/default/types/seantis.translators.translator.xml
seantis/translators/tests/__init__.py
seantis/translators/theme/__init__.py
seantis/translators/theme/configure.zcml
seantis/translators/theme/theme.scss
seantis/translators/types/__init__.py
seantis/translators/types/translator.py
seantis/translators/types/translator.xml