Metadata-Version: 1.1
Name: seantis.translators
Version: 0.4
Summary: A directory of translators working for Zug PD.
Home-page: https://github.com/seantis/seantis.translators
Author: Seantis GmbH
Author-email: Seantis GmbH
License: GPLv2
Keywords: seantis.translators plone
Platform: UNKNOWN
Classifier: Framework :: Plone
Classifier: Framework :: Plone :: 4.3
Classifier: Intended Audience :: Developers
Classifier: License :: OSI Approved :: GNU General Public License v2 (GPLv2)
Classifier: Natural Language :: English
Classifier: Programming Language :: Python :: 2.7
Classifier: Topic :: Software Development :: Libraries :: Python Modules
